{
  "project_info": {
    "project_number": "838146376494",
    "firebase_url": "https://happymommy-rpl.firebaseio.com",
    "project_id": "happymommy-rpl",
    "storage_bucket": "happymommy-rpl.appspot.com"
  },
  "client": [
    {
      "client_info": {
        "mobilesdk_app_id": "1:838146376494:android:d8992739f3746b4c",
        "android_client_info": {
          "package_name": "com.example.happymommy.happymommy"
        }
      },
      "oauth_client": [
        {
          "client_id": "838146376494-83o42ld38aiirauds69cbq11d8rl6g4f.apps.googleusercontent.com",
          "client_type": 3
        }
      ],
      "api_key": [
        {
          "current_key": "AIzaSyDh0PX5c0TbJPvMnCfeVqxw_RMpYhhqQRs"
        }
      ],
      "services": {
        "analytics_service": {
          "status": 1
        },
        "appinvite_service": {
          "status": 1,
          "other_platform_oauth_client": []
        },
        "ads_service": {
          "status": 2
        }
      }
    }
  ],
  "configuration_version": "1"
}